GB0101/LEDLogic/Verilog/indicator.v
module indicator(
	clk,
	rst,
	level,      // A
	button,     // B
	usb,        // D 
	stat,       // F
	pos,        // E
	neg,        // C
	red,
	green);

input clk, rst, level, button, usb, stat, pos, neg;
output red,green;
wire a,b,c,d,e,f;

assign a = level;
assign b = button;
assign c = neg;
assign e = pos;
assign d = usb;
assign f = stat;

assign red = !a&!f | !a&b&!d | !c&!e&!f;
assign green = a&c | a&e&f | !a&c&d;

//assign red = ~(level|(~neg)) | ~(level|(~button)|usb) | ~(neg|pos|(~stat));     //Red table  R = !(A+!C) + !(A+!B+D) + !(C+E+!F)
//assign green = neg | pos&level&button | pos&level&usb;                 //Green table  G = C + !(!E+!A+!B) + !(!E+!A+!D)

/*always @(posedge clk or negedge rst)
begin
    if (!rst)
        red <= 0;
    else
        red <= (~level)&pos&(~stat) | (~level)&button&(~usb) | neg&pos&(~stat);
end

always @(posedge clk or negedge rst)
begin
    if (!rst)
        green <= 0;
    else
        green <= neg | pos&button | pos&level&usb; 
end*/

endmodule

PowerGearV2/Sim/logic/indicator/test.v
`timescale 1us/1ps

/*
STAT TABLE [C,neg(<1.0?),E,pos(>2.0?)]
00	blinking	stat=blk
01	not charging	stat=1
10	charging	stat=0
11	not possible	

BUTTON TABLE
1	pressed
0	released

USB TABLE
1	plugged in
0	not plugged in

LEVEL TABLE
1	full battery
0	not full battery
*/

module test();
	reg clk, rst, level, button, usb, stat, pos, neg;
	wire red,green;

	always @(clk or pos or neg)
	begin
		if (!neg && !pos)
			stat = clk;
		else if (!neg && pos)
			stat = 1;
		else if(neg && !pos)
			stat = 0;
	end

	initial begin
		$dumpfile("my_dumpfile.vcd");
		$dumpvars(0, indicator);
	end

	indicator indicator(.clk(clk),.rst(rst),.level(level),.button(button),.usb(usb),.stat(stat),.pos(pos),.neg(neg),.red(red),.green(green));

	initial begin
			#1 clk = 0; 
		forever begin
			#100	clk =  ! clk; 
		end
	end

	initial begin
		#1		rst = 1; 
		#100	rst=0;
		#100	rst=1;

		//	D			A		B			C,E
		//      no usb plugged in,	low battery,	button released,	not charging  		off
		#1000   usb=0;			level=0;	button=0;		neg=0; pos=1;
		//      no usb plugged in,	low battery,	button pressed,		not charging  		red
		#1000   usb=0;			level=0;	button=1; 		neg=0; pos=1;
		//	no usb plugged in,	full battery,	button released,	not charging 		off
		#100    usb=0;			level=1;	button=0;		neg=0; pos=1;
		//      no usb plugged in,	full battery,	button pressed,		not charging  		green
		#1000   usb=0;			level=1;	button=1;		neg=0; pos=1;

		//      usb plugged in,		low battery,	button released,	charging		green,red	
		#1000   usb=1;			level=0;	button=0;		neg=1; pos=0;
		//      usb plugged in,		low battery,	button pressed,		charging		green,red
		#1000   usb=1;			level=0;	button=1;		neg=1; pos=0;
		//	usb plugged in,		full battery,	button released,	not charging  		green
		#1000   usb=1;			level=1;	button=0;		neg=0; pos=1;
		//      usb plugged in,		full battery,	button pressed,		not charging  		green
		#1000   usb=1;			level=1;	button=1;		neg=0; pos=1;


		//	usb plugged in,		full battery,	button released,	fault 			red blk
		#1000   usb=1;			level=1;	button=0;		neg=0; pos=0;
		//      usb plugged in,		full battery,	button pressed,		fault  			red blk
		#1000   usb=1;			level=1;	button=1;		neg=0; pos=0;
		//      usb plugged in,		low battery,	button released,	fault			red blk
		#1000   usb=1;			level=0;	button=0;		neg=0; pos=0;
		//      usb plugged in,		low battery,	button pressed,		fault			red blk
		#1000   usb=1;			level=0;	button=1;		neg=0; pos=0;

		#1000 $finish;

	end
endmodule

GR-XX02/GearV2BatteryPack/Sim/logic/indicator/my_dumpfile.vcd
$date
	Thu Oct 03 13:58:10 2019
$end
$version
	Icarus Verilog
$end
$timescale
	1ps
$end
$scope module test $end
$scope module indicator $end
$var wire 1 ! a $end
$var wire 1 " b $end
$var wire 1 # button $end
$var wire 1 $ c $end
$var wire 1 % clk $end
$var wire 1 & d $end
$var wire 1 ' e $end
$var wire 1 ( f $end
$var wire 1 ) green $end
$var wire 1 * level $end
$var wire 1 + neg $end
$var wire 1 , pos $end
$var wire 1 - red $end
$var wire 1 . rst $end
$var wire 1 / stat $end
$var wire 1 0 usb $end
$upscope $end
$upscope $end
$enddefinitions $end
#0
$dumpvars
x0
x/
x.
x-
x,
x+
x*
x)
x(
x'
x&
x%
x$
x#
x"
x!
$end
#1000000
1.
0%
#101000000
0.
1%
#201000000
1.
0%
#301000000
1%
#401000000
0%
#501000000
1%
#601000000
0%
#701000000
1%
#801000000
0%
#901000000
1%
#1001000000
0%
#1101000000
1%
#1201000000
0)
0-
0%
1(
1/
1'
1,
0$
0+
0"
0#
0!
0*
0&
00
#1301000000
1%
#1401000000
0%
#1501000000
1%
#1601000000
0%
#1701000000
1%
#1801000000
0%
#1901000000
1%
#2001000000
0%
#2101000000
1%
#2201000000
1-
0%
1"
1#
#2301000000
1%
#2401000000
0%
#2501000000
1%
#2601000000
0%
#2701000000
1%
#2801000000
0%
#2901000000
1%
#3001000000
0%
#3101000000
1%
#3201000000
1)
0-
0%
0"
0#
1!
1*
#3301000000
1%
#3401000000
0%
#3501000000
1%
#3601000000
0%
#3701000000
1%
#3801000000
0%
#3901000000
1%
#4001000000
0%
#4101000000
1%
#4201000000
0%
1"
1#
#4301000000
1%
#4401000000
0%
#4501000000
1%
#4601000000
0%
#4701000000
1%
#4801000000
0%
#4901000000
1%
#5001000000
0%
#5101000000
1%
#5201000000
0)
1-
0%
0(
0/
0"
0#
0!
0*
1&
10
#5301000000
1%
#5401000000
0%
#5501000000
1%
#5601000000
0%
#5701000000
1%
#5801000000
0%
#5901000000
1%
#6001000000
0%
#6101000000
1%
#6201000000
0%
1"
1#
#6301000000
1%
#6401000000
0%
#6501000000
1%
#6601000000
0%
#6701000000
1%
#6801000000
0%
#6901000000
1%
#7001000000
0%
#7101000000
1%
#7201000000
0%
0'
0,
0"
0#
#7301000000
1%
#7401000000
0%
#7501000000
1%
#7601000000
0%
#7701000000
1%
#7801000000
0%
#7901000000
1%
#8001000000
0%
#8101000000
1%
#8201000000
0%
1"
1#
#8301000000
1%
#8401000000
0%
#8501000000
1%
#8601000000
0%
#8701000000
1%
#8801000000
0%
#8901000000
1%
#9001000000
0%
#9101000000
1%
#9201000000
1)
0%
1$
1+
0"
0#
#9301000000
1%
#9401000000
0%
#9501000000
1%
#9601000000
0%
#9701000000
1%
#9801000000
0%
#9901000000
1%
#10001000000
0%
#10101000000
1%
#10201000000
0%
1"
1#
#10301000000
1%
#10401000000
0%
#10501000000
1%
#10601000000
0%
#10701000000
1%
#10801000000
0%
#10901000000
1%
#11001000000
0%
#11101000000
1%
#11201000000
0-
0%
1(
1/
1'
1,
0$
0+
0"
0#
1!
1*
#11301000000
1%
#11401000000
0%
#11501000000
1%
#11601000000
0%
#11701000000
1%
#11801000000
0%
#11901000000
1%
#12001000000
0%
#12101000000
1%
#12201000000
0%
1"
1#
#12301000000
1%
#12401000000
0%
#12501000000
1%
#12601000000
0%
#12701000000
1%
#12801000000
0%
#12901000000
1%
#13001000000
0%
#13101000000
1%
#13201000000
0%
0'
0,
1$
1+
0"
0#
0&
00
#13301000000
1%
#13401000000
0%
#13501000000
1%
#13601000000
0%
#13701000000
1%
#13801000000
0%
#13901000000
1%
#14001000000
0%
#14101000000
1%
#14201000000
0%
1"
1#
#14301000000
1%
#14401000000
0%
#14501000000
1%
#14601000000
0%
#14701000000
1%
#14801000000
0%
#14901000000
1%
#15001000000
0%
#15101000000
1%
#15201000000
0)
0%
0$
0+
0"
0#
#15301000000
1%
#15401000000
0%
#15501000000
1%
#15601000000
0%
#15701000000
1%
#15801000000
0%
#15901000000
1%
#16001000000
0%
#16101000000
1%
#16201000000
0%
1"
1#
#16301000000
1%
#16401000000
0%
#16501000000
1%
#16601000000
0%
#16701000000
1%
#16801000000
0%
#16901000000
1%
#17001000000
0%
#17101000000
1%
#17201000000
1)
0%
1'
1,
0"
0#
#17301000000
1%
#17401000000
0%
#17501000000
1%
#17601000000
0%
#17701000000
1%
#17801000000
0%
#17901000000
1%
#18001000000
0%
#18101000000
1%
#18201000000
0%
1"
1#
#18301000000
1%
#18401000000
0%
#18501000000
1%
#18601000000
0%
#18701000000
1%
#18801000000
0%
#18901000000
1%
#19001000000
0%
#19101000000
1%
#19201000000
0)
0%
0'
0,
1$
1+
0"
0#
0!
0*
#19301000000
1%
#19401000000
0%
#19501000000
1%
#19601000000
0%
#19701000000
1%
#19801000000
0%
#19901000000
1%
#20001000000
0%
#20101000000
1%
#20201000000
1-
0%
1"
1#
#20301000000
1%
#20401000000
0%
#20501000000
1%
#20601000000
0%
#20701000000
1%
#20801000000
0%
#20901000000
1%
#21001000000
0%
#21101000000
1%
#21201000000
0-
0%
0$
0+
0"
0#
#21301000000
1%
#21401000000
0%
#21501000000
1%
#21601000000
0%
#21701000000
1%
#21801000000
0%
#21901000000
1%
#22001000000
0%
#22101000000
1%
#22201000000
1-
0%
1"
1#
#22301000000
1%
#22401000000
0%
#22501000000
1%
#22601000000
0%
#22701000000
1%
#22801000000
0%
#22901000000
1%
#23001000000
0%
#23101000000
1%
#23201000000
0-
0%
1'
1,
0"
0#
#23301000000
1%
#23401000000
0%
#23501000000
1%
#23601000000
0%
#23701000000
1%
#23801000000
0%
#23901000000
1%
#24001000000
0%
#24101000000
1%
#24201000000
1-
0%
1"
1#
#24301000000
1%
#24401000000
0%
#24501000000
1%
#24601000000
0%
#24701000000
1%
#24801000000
0%
#24901000000
1%
#25001000000
0%
#25101000000
1%
#25201000000
0-
0%
1(
1/
0'
0,
1"
1#
0!
0*
1&
10
